{
  "files": 57344,
  "search": 57345,
  "search-view-icon": 57346,
  "source-control": 57347,
  "source-control-view-icon": 57348,
  "debug-alt": 57349,
  "run-view-icon": 57350,
  "extensions": 57351,
  "extensions-view-icon": 57352,
  "account": 57353,
  "settings-gear": 57354,
  "settings-view-bar-icon": 57355,
  "chevron-up": 57356,
  "chevron-down": 57357,
  "chevron-left": 57358,
  "chevron-right": 57359,
  "arrow-up": 57360,
  "arrow-down": 57361,
  "arrow-left": 57362,
  "arrow-right": 57363,
  "fold": 57364,
  "unfold": 57365,
  "expand-all": 57366,
  "collapse-all": 57367,
  "add": 57368,
  "plus": 57369,
  "remove": 57370,
  "close": 57371,
  "close-all": 57372,
  "trash": 57373,
  "clear-all": 57374,
  "check": 57375,
  "pass": 57376,
  "error": 57377,
  "warning": 57378,
  "info": 57379,
  "question": 57380,
  "new-file": 57381,
  "new-folder": 57382,
  "save": 57383,
  "file": 57384,
  "folder": 57385,
  "folder-opened": 57386,
  "edit": 57387,
  "pencil": 57388,
  "copy": 57389,
  "comment": 57390,
  "eye": 57391,
  "eye-closed": 57392,
  "git-branch": 57393,
  "git-commit": 57394,
  "git-merge": 57395,
  "git-compare": 57396,
  "git-pull-request": 57397,
  "github": 57398,
  "bug": 57399,
  "play": 57400,
  "debug-start": 57401,
  "debug-continue": 57402,
  "debug-pause": 57403,
  "debug-stop": 57404,
  "debug-restart": 57405,
  "debug-disconnect": 57406,
  "debug-step-into": 57407,
  "debug-step-out": 57408,
  "debug-step-over": 57409,
  "stop": 57410,
  "stop-circle": 57411,
  "record": 57412,
  "record-keys": 57413,
  "terminal": 57414,
  "terminal-bash": 57415,
  "bell": 57416,
  "bell-dot": 57417,
  "heart": 57418,
  "star-empty": 57419,
  "star-full": 57420,
  "bookmark": 57421,
  "tag": 57422,
  "filter": 57423,
  "refresh": 57424,
  "sync": 57425,
  "lock": 57426,
  "unlock": 57427,
  "menu": 57428,
  "ellipsis": 57429,
  "kebab-vertical": 57430,
  "home": 57431,
  "globe": 57432,
  "key": 57433,
  "gear": 57434,
  "tools": 57435,
  "lightbulb": 57436,
  "pin": 57437,
  "pinned": 57438,
  "unpin": 57439,
  "clock": 57440,
  "history": 57441,
  "calendar": 57442,
  "layout-sidebar-left": 57443,
  "layout-sidebar-right": 57444,
  "chrome-close": 57445,
  "chrome-minimize": 57446,
  "chrome-maximize": 57447,
  "chrome-restore": 57448,
  "screen-full": 57449,
  "screen-normal": 57450,
  "cloud": 57451,
  "cloud-download": 57452,
  "cloud-upload": 57453,
  "desktop-download": 57454,
  "archive": 57455,
  "package": 57456,
  "repo": 57457,
  "library": 57458,
  "code": 57459,
  "go-to-file": 57460,
  "file-code": 57461,
  "export": 57462,
  "import": 57463,
  "discard": 57464,
  "link": 57465,
  "link-external": 57466,
  "share": 57467,
  "mail": 57468,
  "mail-read": 57469,
  "inbox": 57470,
  "reply": 57471,
  "comment-discussion": 57472,
  "note": 57473,
  "notebook": 57474,
  "output": 57475,
  "console": 57476,
  "sign-in": 57477,
  "sign-out": 57478,
  "feedback": 57479,
  "thumbsup": 57480,
  "thumbsdown": 57481,
  "loading": 57482,
  "search-stop": 57483,
  "zoom-in": 57484,
  "zoom-out": 57485,
  "window": 61697,
  "vr": 61698,
  "tags": 61699,
  "rocket": 61700,
  "remote": 61701,
  "play-circle": 61702,
  "pie-chart": 61703,
  "person": 61704,
  "mute": 61705,
  "multiple-windows": 61706,
  "more": 61707,
  "mirror": 61708,
  "layout": 61709,
  "git-pull-request-draft": 61710,
  "git-pull-request-closed": 61711,
  "folder-library": 61712,
  "file-zip": 61713,
  "debug-alt-small": 61714,
  "compass": 61715,
  "circle": 61716,
  "chat": 61717
}